skill_ovos_randomness/__init__.py
skill_ovos_randomness/coin-flip.wav
skill_ovos_randomness/die-roll.wav
skill_ovos_randomness/magic.mp3
skill_ovos_randomness/version.py
skill_ovos_randomness/locale/en-us/dialog/choice-result.dialog
skill_ovos_randomness/locale/en-us/dialog/coin-result.dialog
skill_ovos_randomness/locale/en-us/dialog/die-result.dialog
skill_ovos_randomness/locale/en-us/dialog/first-choice.dialog
skill_ovos_randomness/locale/en-us/dialog/fortune-query.dialog
skill_ovos_randomness/locale/en-us/dialog/fortune-result.dialog
skill_ovos_randomness/locale/en-us/dialog/multiple-die-result.dialog
skill_ovos_randomness/locale/en-us/dialog/number-range-not-specified.dialog
skill_ovos_randomness/locale/en-us/dialog/number-result.dialog
skill_ovos_randomness/locale/en-us/dialog/over-dice-limit.dialog
skill_ovos_randomness/locale/en-us/dialog/second-choice.dialog
skill_ovos_randomness/locale/en-us/intents/flip-a-coin.intent
skill_ovos_randomness/locale/en-us/intents/fortune-teller.intent
skill_ovos_randomness/locale/en-us/intents/make-a-choice.intent
skill_ovos_randomness/locale/en-us/intents/pick-a-number.intent
skill_ovos_randomness/locale/en-us/intents/roll-multiple-dice.intent
skill_ovos_randomness/locale/en-us/intents/roll-single-die.intent
skill_ovos_randomness/locale/eu/dialog/choice-result.dialog
skill_ovos_randomness/locale/eu/dialog/coin-result.dialog
skill_ovos_randomness/locale/eu/dialog/die-result.dialog
skill_ovos_randomness/locale/eu/dialog/first-choice.dialog
skill_ovos_randomness/locale/eu/dialog/fortune-query.dialog
skill_ovos_randomness/locale/eu/dialog/fortune-result.dialog
skill_ovos_randomness/locale/eu/dialog/multiple-die-result.dialog
skill_ovos_randomness/locale/eu/dialog/number-range-not-specified.dialog
skill_ovos_randomness/locale/eu/dialog/number-result.dialog
skill_ovos_randomness/locale/eu/dialog/over-dice-limit.dialog
skill_ovos_randomness/locale/eu/dialog/second-choice.dialog
ovos_skill_randomness-0.1.2.dist-info/METADATA
ovos_skill_randomness-0.1.2.dist-info/WHEEL
ovos_skill_randomness-0.1.2.dist-info/entry_points.txt
ovos_skill_randomness-0.1.2.dist-info/top_level.txt
ovos_skill_randomness-0.1.2.dist-info/RECORD
