Metadata-Version: 2.1
Name: ovos-skill-randomness
Version: 0.1.2
Home-page: https://github.com/openvoiceos/skill-ovos-randomness
Author: OpenVoiceOS
Author-email: mike@oscillatelabs.net
License: MIT
Keywords: ovos skill voice assistant
Requires-Dist: ovos-utils
Requires-Dist: ovos-workshop
Requires-Dist: ovos-number-parser<1.0.0,>=0.0.1
Requires-Dist: icepool
Provides-Extra: test
Requires-Dist: pytest; extra == "test"
Requires-Dist: ovos-plugin-manager; extra == "test"
Requires-Dist: padacioso; extra == "test"
